fastq2bcl/__init__.py
fastq2bcl/cli.py
fastq2bcl/parser.py
fastq2bcl/reader.py
fastq2bcl/writer.py
fastq2bcl-0.3.dist-info/LICENSE.txt
fastq2bcl-0.3.dist-info/METADATA
fastq2bcl-0.3.dist-info/WHEEL
fastq2bcl-0.3.dist-info/entry_points.txt
fastq2bcl-0.3.dist-info/top_level.txt
fastq2bcl-0.3.dist-info/RECORD
