Metadata-Version: 2.1
Name: fastq2bcl
Version: 0.3
Summary: fastq2bcl convert fastq files in a bcl2fastq-able run directory
Home-page: https://github.com/tucano/fastq2bcl/
Author: Davide Rambaldi
Author-email: davide.rambaldi@fht.org
License: MIT
Project-URL: Documentation, https://fastq2bcl.readthedocs.io/en/stable/
Project-URL: Source, https://github.com/tucano/fastq2bcl/
Project-URL: Changelog, https://fastq2bcl.readthedocs.io/en/stable/changelog.html
Project-URL: Tracker, https://github.com/tucano/fastq2bcl/issues
Project-URL: Download, https://pypi.org/project/fastq2bcl/#files
Platform: any
Classifier: Development Status :: 2 - Pre-Alpha
Classifier: Programming Language :: Python
Classifier: Topic :: Scientific/Engineering :: Bio-Informatics
Requires-Python: >=3.8
License-File: LICENSE.txt
Requires-Dist: biopython
Requires-Dist: rich
Requires-Dist: importlib-metadata ; python_version >= "3.8"
Provides-Extra: testing
Requires-Dist: setuptools ; extra == 'testing'
Requires-Dist: pytest ; extra == 'testing'
Requires-Dist: pytest-cov ; extra == 'testing'
